bert_serving/__init__.py
bert_serving/server/__init__.py
bert_serving/server/benchmark.py
bert_serving/server/graph.py
bert_serving/server/helper.py
bert_serving/server/http.py
bert_serving/server/zmq_decor.py
bert_serving/server/bert/__init__.py
bert_serving/server/bert/extract_features.py
bert_serving/server/bert/modeling.py
bert_serving/server/bert/optimization.py
bert_serving/server/bert/tokenization.py
bert_serving/server/cli/__init__.py
bert_serving_server-1.9.9.dist-info/METADATA
bert_serving_server-1.9.9.dist-info/WHEEL
bert_serving_server-1.9.9.dist-info/entry_points.txt
bert_serving_server-1.9.9.dist-info/top_level.txt
bert_serving_server-1.9.9.dist-info/RECORD
