Metadata-Version: 2.1
Name: bert-serving-server
Version: 1.9.9
Summary: Mapping a variable-length sentence to a fixed-length vector using BERT model (Server)
Home-page: https://github.com/hanxiao/bert-as-service
Author: Han Xiao
Author-email: artex.xh@gmail.com
License: MIT
Keywords: bert nlp tensorflow machine learning sentence encoding embedding serving
Platform: UNKNOWN
Classifier: Programming Language :: Python :: 3.6
Classifier: License :: OSI Approved :: MIT License
Classifier: Operating System :: OS Independent
Classifier: Topic :: Scientific/Engineering :: Artificial Intelligence
Requires-Dist: numpy
Requires-Dist: six
Requires-Dist: pyzmq (>=17.1.0)
Requires-Dist: GPUtil (>=1.3.0)
Requires-Dist: termcolor (>=1.1)
Provides-Extra: cpu
Requires-Dist: tensorflow (>=1.10.0) ; extra == 'cpu'
Provides-Extra: gpu
Requires-Dist: tensorflow-gpu (>=1.10.0) ; extra == 'gpu'
Provides-Extra: http
Requires-Dist: flask ; extra == 'http'
Requires-Dist: flask-compress ; extra == 'http'
Requires-Dist: flask-cors ; extra == 'http'
Requires-Dist: flask-json ; extra == 'http'
Requires-Dist: bert-serving-client ; extra == 'http'
